swagger_client/__init__.py
swagger_client/api_client.py
swagger_client/configuration.py
swagger_client/rest.py
swagger_client/api/__init__.py
swagger_client/api/custom_speech_datasets_for_model_adaptation_api.py
swagger_client/api/custom_speech_endpoints_api.py
swagger_client/api/custom_speech_model_evaluations_api.py
swagger_client/api/custom_speech_models_api.py
swagger_client/api/custom_speech_projects_api.py
swagger_client/api/custom_speech_transcriptions_api.py
swagger_client/api/custom_speech_web_hooks_api.py
swagger_client/api/service_health_api.py
swagger_client/models/__init__.py
swagger_client/models/component.py
swagger_client/models/dataset.py
swagger_client/models/dataset_kind.py
swagger_client/models/dataset_locales.py
swagger_client/models/dataset_properties.py
swagger_client/models/dataset_update.py
swagger_client/models/detailed_error_code.py
swagger_client/models/endpoint.py
swagger_client/models/endpoint_links.py
swagger_client/models/endpoint_properties.py
swagger_client/models/endpoint_properties_update.py
swagger_client/models/endpoint_update.py
swagger_client/models/entity_error.py
swagger_client/models/entity_reference.py
swagger_client/models/error.py
swagger_client/models/error_code.py
swagger_client/models/evaluation.py
swagger_client/models/evaluation_properties.py
swagger_client/models/evaluation_update.py
swagger_client/models/file.py
swagger_client/models/file_kind.py
swagger_client/models/file_links.py
swagger_client/models/file_properties.py
swagger_client/models/health_status.py
swagger_client/models/inner_error.py
swagger_client/models/links.py
swagger_client/models/model.py
swagger_client/models/model_copy.py
swagger_client/models/model_deprecation_dates.py
swagger_client/models/model_file.py
swagger_client/models/model_links.py
swagger_client/models/model_manifest.py
swagger_client/models/model_properties.py
swagger_client/models/model_update.py
swagger_client/models/paginated_datasets.py
swagger_client_ppl-1.0.0.dist-info/METADATA
swagger_client_ppl-1.0.0.dist-info/WHEEL
swagger_client_ppl-1.0.0.dist-info/top_level.txt
swagger_client_ppl-1.0.0.dist-info/RECORD
